Metadata-Version: 1.1
Name: fred-pain
Version: 0.0.1
Summary: PAIN interface for FRED
Home-page: https://fred.nic.cz
Author: Jan Musílek
Author-email: jan.musilek@nic.cz
License: UNKNOWN
Platform: UNKNOWN
Classifier: Development Status :: 2 - Pre-Alpha
Classifier: Environment :: Plugins
Classifier: Intended Audience :: Developers
Classifier: License :: OSI Approved :: GNU General Public License v3 or later (GPLv3+)
Classifier: Operating System :: OS Independent
Classifier: Programming Language :: Python
Classifier: Programming Language :: Python :: 3.5
Classifier: Programming Language :: Python :: 3.6
